paper_forms/__init__.py
paper_forms/boundfield.py
paper_forms/composer.py
paper_forms/conf.py
paper_forms/utils.py
paper_forms/templatetags/__init__.py
paper_forms/templatetags/paper_forms.py
paper_forms-0.5.3.dist-info/LICENSE
paper_forms-0.5.3.dist-info/METADATA
paper_forms-0.5.3.dist-info/WHEEL
paper_forms-0.5.3.dist-info/top_level.txt
paper_forms-0.5.3.dist-info/RECORD
